RoboCup/__init__.py
robocup_tools-0.0.1.dist-info/LICENSE
robocup_tools-0.0.1.dist-info/METADATA
robocup_tools-0.0.1.dist-info/WHEEL
robocup_tools-0.0.1.dist-info/top_level.txt
robocup_tools-0.0.1.dist-info/RECORD
